{ "Dialogues": [
  {
    "Avatar": "RN-570",
    "Name": "RN-570",
    "Emotion": "normal",
    "Text": "¡Una niña humana! "
  }, {
    "Avatar": "Suri",
    "Name": "Suri",
    "Emotion": "surprised",
    "Text": "¿Un robot?"
  }, {
    "Avatar": "Chapu",
    "Name": "Chapu",
    "Emotion": "mad",
    "Text": "¡Grrr!"
  }, {
    "Avatar": "RN-570",
    "Name": "RN-570",
    "Emotion": "normal",
    "Text": "Soy RN-570, androide de reciclaje, ESTADO ACTUAL: obsoleto, reparado y reciclado para cumplir misión.. ¡bip!"
  }, {
    "Avatar": "RN-570",
    "Name": "RN-570",
    "Emotion": "normal",
    "Text": "MISIÓN ACTUAL: avisar a humanos del pasado sobre desastre ecológico. ¡bip!..."
  }, {
    "Avatar": "Suri",
    "Name": "Suri",
    "Emotion": "cry",
    "Text": "¿Que hiciste con mi abuelo?"
  }, {
    "Avatar": "RN-570",
    "Name": "RN-570",
    "Emotion": "normal",
    "Text": "Último humano anciano visto cruzando portal del tiempo por el que RN-570 vino al pasado.."
  }, {
    "Avatar": "RN-570",
    "Name": "RN-570",
    "Emotion": "normal",
    "Text": "...el humano me dio un bastonazo.. luego se fue enojado."
  }, {
    "Avatar": "RN-570",
    "Name": "RN-570",
    "Emotion": "normal",
    "Text": "El anciano tiene poca capacidad visual.. y poca paciencia por cierto."
  }, {
    "Avatar": "Suri",
    "Name": "Suri",
    "Emotion": "sad",
    "Text": "¡Debemos ir a buscar al abuelito Chapu! Crucemos por este portal que dice este robot."
  }, {
    "Avatar": "Chapu",
    "Name": "Chapu",
    "Emotion": "mad",
    "Text": "¡Guau! ¡Guau!"
  }
] }
